isaacbao_mcp_server_demo/__init__.py
isaacbao_mcp_server_demo-0.1.0.dist-info/WHEEL
isaacbao_mcp_server_demo-0.1.0.dist-info/entry_points.txt
isaacbao_mcp_server_demo-0.1.0.dist-info/METADATA
isaacbao_mcp_server_demo-0.1.0.dist-info/RECORD
