Metadata-Version: 2.3
Name: isaacbao-mcp-server-demo
Version: 0.1.0
Summary: Add your description here
Author: Ganzhe
Author-email: Ganzhe <1959006169@qq.com>
Requires-Dist: mcp[cli]>=1.12.3
Requires-Python: >=3.13
